{
"type": "FeatureCollection",
"name": "18-06-44-troops",
"crs": { "type": "name", "properties": { "name": "urn:ogc:def:crs:OGC:1.3:CRS84" } },
"features": [
{ "type": "Feature", "properties": { "id": 22, "name": "82nd Airborne Division", "country": "US", "front": 0 }, "geometry": { "type": "Point", "coordinates": [ -1.478722584933616, 49.394743924886789 ] } },
{ "type": "Feature", "properties": { "id": 23, "name": "90th Infantry Division", "country": "US", "front": 0 }, "geometry": { "type": "Point", "coordinates": [ -1.476309461331746, 49.430853676594573 ] } },
{ "type": "Feature", "properties": { "id": 22, "name": "82nd Airborne Division", "country": "US", "front": 1 }, "geometry": { "type": "Point", "coordinates": [ -1.546290045785981, 49.386366854923061 ] } },
{ "type": "Feature", "properties": { "id": 1, "name": "101st Airborne Division", "country": "US", "front": 0 }, "geometry": { "type": "Point", "coordinates": [ -1.259932711697388, 49.344460075677318 ] } },
{ "type": "Feature", "properties": { "id": 1, "name": "101st Airborne Division", "country": "US", "front": 1 }, "geometry": { "type": "Point", "coordinates": [ -1.300955812929181, 49.298845906192987 ] } },
{ "type": "Feature", "properties": { "id": 31, "name": "9th Infantry Division", "country": "US", "front": 1 }, "geometry": { "type": "Point", "coordinates": [ -1.695803162285171, 49.379821275036051 ] } },
{ "type": "Feature", "properties": { "id": 31, "name": "9th Infantry Division", "country": "US", "front": 0 }, "geometry": { "type": "Point", "coordinates": [ -1.584296742515436, 49.391799024053419 ] } },
{ "type": "Feature", "properties": { "id": 8, "name": "29th Infantry Division", "country": "US", "front": 1 }, "geometry": { "type": "Point", "coordinates": [ -1.041545025728139, 49.179630632206667 ] } },
{ "type": "Feature", "properties": { "id": 8, "name": "29th Infantry Division", "country": "US", "front": 0 }, "geometry": { "type": "Point", "coordinates": [ -1.023044411447134, 49.25948943086167 ] } },
{ "type": "Feature", "properties": { "id": 10, "name": "2nd Infantry Division", "country": "US", "front": 1 }, "geometry": { "type": "Point", "coordinates": [ -0.954672576060813, 49.160697804103258 ] } },
{ "type": "Feature", "properties": { "id": 10, "name": "2nd Infantry Division", "country": "US", "front": 0 }, "geometry": { "type": "Point", "coordinates": [ -0.934965399978874, 49.194351159802729 ] } },
{ "type": "Feature", "properties": { "id": 5, "name": "1st Infantry Division", "country": "US", "front": 1 }, "geometry": { "type": "Point", "coordinates": [ -0.842864515840829, 49.111754483713447 ] } },
{ "type": "Feature", "properties": { "id": 5, "name": "1st Infantry Division", "country": "US", "front": 0 }, "geometry": { "type": "Point", "coordinates": [ -0.825168276093781, 49.182785399662713 ] } },
{ "type": "Feature", "properties": { "id": 9, "name": "2nd Armored Division", "country": "US", "front": 1 }, "geometry": { "type": "Point", "coordinates": [ -0.891126987878232, 49.172268726052998 ] } },
{ "type": "Feature", "properties": { "id": 13, "name": "4th Infantry Division", "country": "US", "front": 0 }, "geometry": { "type": "Point", "coordinates": [ -1.325087048947882, 49.49620225289727 ] } },
{ "type": "Feature", "properties": { "id": 13, "name": "4th Infantry Division", "country": "US", "front": 1 }, "geometry": { "type": "Point", "coordinates": [ -1.330717670685579, 49.458049271305228 ] } },
{ "type": "Feature", "properties": { "id": 23, "name": "90th Infantry Division", "country": "US", "front": 1 }, "geometry": { "type": "Point", "coordinates": [ -1.419198869420819, 49.461186253913873 ] } },
{ "type": "Feature", "properties": { "id": 29, "name": "VII Corps", "country": "US", "front": 0 }, "geometry": { "type": "Point", "coordinates": [ -1.312217056404575, 49.425098829314997 ] } },
{ "type": "Feature", "properties": { "id": 9, "name": "2nd Armored Division", "country": "US", "front": 0 }, "geometry": { "type": "Point", "coordinates": [ -0.887909489742406, 49.231395951188865 ] } },
{ "type": "Feature", "properties": { "id": 36, "name": "First Army", "country": "US", "front": 0 }, "geometry": { "type": "Point", "coordinates": [ -0.992643983323386, 49.392871799621048 ] } },
{ "type": "Feature", "properties": { "id": 28, "name": "V Corps", "country": "US", "front": 0 }, "geometry": { "type": "Point", "coordinates": [ -0.900377295018735, 49.283369439713212 ] } },
{ "type": "Feature", "properties": { "id": 30, "name": "XXX Corps", "country": "UK", "front": 0 }, "geometry": { "type": "Point", "coordinates": [ -0.655847436695891, 49.249251602575562 ] } },
{ "type": "Feature", "properties": { "id": 14, "name": "50th Infantry Division", "country": "UK", "front": 0 }, "geometry": { "type": "Point", "coordinates": [ -0.694481195874604, 49.248075405632477 ] } },
{ "type": "Feature", "properties": { "id": 37, "name": "49th Infantry Division", "country": "UK", "front": 1 }, "geometry": { "type": "Point", "coordinates": [ -0.595117159382158, 49.219182119800749 ] } },
{ "type": "Feature", "properties": { "id": 37, "name": "49th Infantry Division", "country": "UK", "front": 0 }, "geometry": { "type": "Point", "coordinates": [ -0.637346822414887, 49.245575966791115 ] } },
{ "type": "Feature", "properties": { "id": 14, "name": "50th Infantry Division", "country": "UK", "front": 1 }, "geometry": { "type": "Point", "coordinates": [ -0.696066163393728, 49.196979364599301 ] } },
{ "type": "Feature", "properties": { "id": 21, "name": "7th Armoured Division", "country": "UK", "front": 1 }, "geometry": { "type": "Point", "coordinates": [ -0.768862058716811, 49.120704721824367 ] } },
{ "type": "Feature", "properties": { "id": 21, "name": "7th Armoured Division", "country": "UK", "front": 0 }, "geometry": { "type": "Point", "coordinates": [ -0.775699242255443, 49.145704180204284 ] } },
{ "type": "Feature", "properties": { "id": 6, "name": "21st Army Group", "country": "UK", "front": 0 }, "geometry": { "type": "Point", "coordinates": [ -0.552887496349431, 49.285468228382456 ] } },
{ "type": "Feature", "properties": { "id": 11, "name": "3rd Canadian Infantry Division", "country": "CA", "front": 0 }, "geometry": { "type": "Point", "coordinates": [ -0.459177863143473, 49.242031344561788 ] } },
{ "type": "Feature", "properties": { "id": 11, "name": "3rd Canadian Infantry Division", "country": "CA", "front": 1 }, "geometry": { "type": "Point", "coordinates": [ -0.514679705986486, 49.213402480811709 ] } },
{ "type": "Feature", "properties": { "id": 12, "name": "3rd Infantry Division", "country": "UK", "front": 1 }, "geometry": { "type": "Point", "coordinates": [ -0.350982927332416, 49.235667105402328 ] } },
{ "type": "Feature", "properties": { "id": 12, "name": "3rd Infantry Division", "country": "UK", "front": 0 }, "geometry": { "type": "Point", "coordinates": [ -0.297096394551194, 49.264082638014749 ] } },
{ "type": "Feature", "properties": { "id": 27, "name": "I Corps", "country": "UK", "front": 0 }, "geometry": { "type": "Point", "coordinates": [ -0.347771990190467, 49.30081290556285 ] } },
{ "type": "Feature", "properties": { "id": 15, "name": "51st Infantry Division", "country": "UK", "front": 1 }, "geometry": { "type": "Point", "coordinates": [ -0.245616424377964, 49.218131326615385 ] } },
{ "type": "Feature", "properties": { "id": 15, "name": "51st Infantry Division", "country": "UK", "front": 0 }, "geometry": { "type": "Point", "coordinates": [ -0.270552034930622, 49.270381198349234 ] } },
{ "type": "Feature", "properties": { "id": 17, "name": "6th Airborne Division", "country": "UK", "front": 0 }, "geometry": { "type": "Point", "coordinates": [ -0.248029547979834, 49.258045763174138 ] } },
{ "type": "Feature", "properties": { "id": 17, "name": "6th Airborne Division", "country": "UK", "front": 1 }, "geometry": { "type": "Point", "coordinates": [ -0.264519225925947, 49.243606763631895 ] } },
{ "type": "Feature", "properties": { "id": 38, "name": "Second Army", "country": "UK", "front": 0 }, "geometry": { "type": "Point", "coordinates": [ -0.53599563113634, 49.304353306588879 ] } },
{ "type": "Feature", "properties": { "id": 32, "name": "21st Panzer Division", "country": "GE", "front": 1 }, "geometry": { "type": "Point", "coordinates": [ -0.353402611928164, 49.200527219562488 ] } },
{ "type": "Feature", "properties": { "id": 97, "name": "346th Infantry Division", "country": "GE", "front": 1 }, "geometry": { "type": "Point", "coordinates": [ -0.177646776258621, 49.167929947191162 ] } },
{ "type": "Feature", "properties": { "id": 39, "name": "711th Infantry Division", "country": "GE", "front": 1 }, "geometry": { "type": "Point", "coordinates": [ -0.179255525326534, 49.248857797544119 ] } },
{ "type": "Feature", "properties": { "id": 40, "name": "Panzer Lehr Division", "country": "GE", "front": 1 }, "geometry": { "type": "Point", "coordinates": [ -0.657858373030783, 49.112281013013444 ] } },
{ "type": "Feature", "properties": { "id": 41, "name": "17th Panzer Division", "country": "GE", "front": 1 }, "geometry": { "type": "Point", "coordinates": [ -1.251888966357821, 49.266838357098678 ] } },
{ "type": "Feature", "properties": { "id": 35, "name": "LXXXIV Army Corps", "country": "GE", "front": 0 }, "geometry": { "type": "Point", "coordinates": [ -1.090113249145533, 49.111475499918946 ] } },
{ "type": "Feature", "properties": { "id": 42, "name": "352nd Infantry Division", "country": "GE", "front": 0 }, "geometry": { "type": "Point", "coordinates": [ -1.09543811950324, 49.132284985671738 ] } },
{ "type": "Feature", "properties": { "id": 19, "name": "709th Static Infantry Division", "country": "GE", "front": 0 }, "geometry": { "type": "Point", "coordinates": [ -1.381694906775112, 49.533803479451493 ] } },
{ "type": "Feature", "properties": { "id": 7, "name": "243rd Static Infantry Division", "country": "GE", "front": 1 }, "geometry": { "type": "Point", "coordinates": [ -1.742456885254655, 49.44942153369135 ] } },
{ "type": "Feature", "properties": { "id": 26, "name": "91st Infantry Division", "country": "GE", "front": 1 }, "geometry": { "type": "Point", "coordinates": [ -1.498027573748577, 49.340267433197319 ] } },
{ "type": "Feature", "properties": { "id": 33, "name": "716th Static Infantry Division", "country": "GE", "front": 1 }, "geometry": { "type": "Point", "coordinates": [ -0.445905683333187, 49.19947602980946 ] } },
{ "type": "Feature", "properties": { "id": 45, "name": "3rd Parachute Division", "country": "GE", "front": 1 }, "geometry": { "type": "Point", "coordinates": [ -0.893540111480103, 49.070667979765439 ] } },
{ "type": "Feature", "properties": { "id": 34, "name": "12th Panzer Division", "country": "GE", "front": 1 }, "geometry": { "type": "Point", "coordinates": [ -0.583855915906765, 49.168981807286016 ] } },
{ "type": "Feature", "properties": { "id": 46, "name": "2nd Panzer Division", "country": "GE", "front": 0 }, "geometry": { "type": "Point", "coordinates": [ -0.764035811513071, 49.046948759284533 ] } },
{ "type": "Feature", "properties": { "id": 47, "name": "77th Infantry Division", "country": "GE", "front": 0 }, "geometry": { "type": "Point", "coordinates": [ -1.466556420107535, 49.471902762729727 ] } },
{ "type": "Feature", "properties": { "id": 48, "name": "30th Infantry Division", "country": "US", "front": 0 }, "geometry": { "type": "Point", "coordinates": [ -1.1835171309715, 49.295173963980645 ] } },
{ "type": "Feature", "properties": { "id": 49, "name": "XIX Corps", "country": "US", "front": 0 }, "geometry": { "type": "Point", "coordinates": [ -1.05361064373749, 49.277072537704271 ] } },
{ "type": "Feature", "properties": { "id": 48, "name": "30th Infantry DivisionL", "country": "US", "front": 1 }, "geometry": { "type": "Point", "coordinates": [ -1.123993415458703, 49.265788577499841 ] } },
{ "type": "Feature", "properties": { "id": 51, "name": "15th (Scottish) Infantry Division", "country": "UK", "front": 0 }, "geometry": { "type": "Point", "coordinates": [ -0.618041833599925, 49.267100798508537 ] } },
{ "type": "Feature", "properties": { "id": 50, "name": "11th Armoured Division", "country": "UK", "front": 0 }, "geometry": { "type": "Point", "coordinates": [ -0.51146220785066, 49.24308162952633 ] } },
{ "type": "Feature", "properties": { "id": 52, "name": "79th Infantry Division", "country": "US", "front": 1 }, "geometry": { "type": "Point", "coordinates": [ -1.405524502343554, 49.365417929998571 ] } },
{ "type": "Feature", "properties": { "id": 88, "name": "30th Mobile Brigade", "country": "GE", "front": 1 }, "geometry": { "type": "Point", "coordinates": [ -0.908923016179399, 49.038611168268652 ] } },
{ "type": "Feature", "properties": { "id": 89, "name": "265th Infantry Division", "country": "GE", "front": 1 }, "geometry": { "type": "Point", "coordinates": [ -1.448960727177217, 49.31248215369547 ] } },
{ "type": "Feature", "properties": { "id": 90, "name": "275th Infantry Division", "country": "GE", "front": 1 }, "geometry": { "type": "Point", "coordinates": [ -1.193973999912937, 49.251089317855872 ] } },
{ "type": "Feature", "properties": { "id": 91, "name": "VIII Corps", "country": "UK", "front": 0 }, "geometry": { "type": "Point", "coordinates": [ -0.561534522589466, 49.251483105087466 ] } },
{ "type": "Feature", "properties": { "id": 92, "name": "VIII Corps", "country": "US", "front": 0 }, "geometry": { "type": "Point", "coordinates": [ -1.271998329706739, 49.379035746855578 ] } },
{ "type": "Feature", "properties": { "id": 93, "name": "319th Static Infantry Division", "country": "GE", "front": 1 }, "geometry": { "type": "Point", "coordinates": [ -1.310105573252973, 49.535108558320111 ] } },
{ "type": "Feature", "properties": { "id": 94, "name": "XLVII Panzer Corps", "country": "GE", "front": 0 }, "geometry": { "type": "Point", "coordinates": [ -0.61683527179899, 48.876232900976355 ] } },
{ "type": "Feature", "properties": { "id": 95, "name": "I SS Panzer Corps", "country": "GE", "front": 0 }, "geometry": { "type": "Point", "coordinates": [ -0.377974934868875, 48.969083055327864 ] } },
{ "type": "Feature", "properties": { "id": 96, "name": "2nd SS Panzer Division Das Reich", "country": "GE", "front": 0 }, "geometry": { "type": "Point", "coordinates": [ -0.95065070339103, 49.01002969362851 ] } },
{ "type": "Feature", "properties": { "id": 87, "name": "245th Infantry Division", "country": "GE", "front": 0 }, "geometry": { "type": "Point", "coordinates": [ -1.301442559198514, 49.043866533968128 ] } },
{ "type": "Feature", "properties": { "id": 98, "name": "353rd Infantry Division", "country": "GE", "front": 1 }, "geometry": { "type": "Point", "coordinates": [ -1.031590890870425, 49.095297627062671 ] } },
{ "type": "Feature", "properties": { "id": 99, "name": "XII Corps", "country": "UK", "front": 0 }, "geometry": { "type": "Point", "coordinates": [ -0.515029487405063, 49.30493599505526 ] } },
{ "type": "Feature", "properties": { "id": 8, "name": "29th Infantry Division", "country": "US", "front": 0 }, "geometry": { "type": "Point", "coordinates": [ -1.405007771009628, 49.387830787009975 ] } }
]
}
