{"type":"FeatureCollection","features":[{"type":"Feature","geometry":{"type":"Point","coordinates":["-0.83350","49.27089"]},"properties":{"Date":"1944-07-18T00:00:00.000Z","Notes":"","UID":0,"SN":"Twenty-First","MID":4,"UT":"Infantry","UC":"GB","US":"Army Group","LN":"Twenty-First Army Group"}},{"type":"Feature","geometry":{"type":"Point","coordinates":["-0.24961","49.26208"]},"properties":{"Date":"1944-07-18T00:00:00.000Z","Notes":"","UID":0,"SN":"6","MID":1,"UT":"Airborne","UC":"GB","US":"Division","LN":"6th Airborne Division"}},{"type":"Feature","geometry":{"type":"Point","coordinates":["-0.62847","49.18134"]},"properties":{"Date":"1944-07-18T00:00:00.000Z","Notes":"","UID":0,"SN":"49","MID":6,"UT":"Infantry","UC":"GB","US":"Division","LN":"49th Infantry Division"}},{"type":"Feature","geometry":{"type":"Point","coordinates":["-0.26496","49.23158"]},"properties":{"Date":"1944-07-18T00:00:00.000Z","Notes":"","UID":0,"SN":"51","MID":6,"UT":"Infantry","UC":"GB","US":"Division","LN":"51st Infantry Division"}},{"type":"Feature","geometry":{"type":"Point","coordinates":["-0.46804","49.24860"]},"properties":{"Date":"1944-07-18T00:00:00.000Z","Notes":"","UID":0,"SN":"II","MID":35,"UT":"Infantry","UC":"CAN","US":"Corp","LN":"Second Corps"}},{"type":"Feature","geometry":{"type":"Point","coordinates":["-0.21295","49.14352"]},"properties":{"Date":"1944-07-18T00:00:00.000Z","Notes":"GAF","UID":0,"SN":"16 LW","MID":22,"UT":"Infantry","UC":"GMN","US":"Division","LN":"16th Luftwaffe Division"}},{"type":"Feature","geometry":{"type":"Point","coordinates":["-0.65705","49.21312"]},"properties":{"Date":"1944-07-18T00:00:00.000Z","Notes":"","UID":0,"SN":"7","MID":2,"UT":"Armoured","UC":"GB","US":"Division","LN":"7th Armoured Division"}},{"type":"Feature","geometry":{"type":"Point","coordinates":["-0.53576","49.12604"]},"properties":{"Date":"1944-07-18T00:00:00.000Z","Notes":"","UID":0,"SN":"53","MID":6,"UT":"Infantry","UC":"GB","US":"Division","LN":"53rd Infantry Division"}},{"type":"Feature","geometry":{"type":"Point","coordinates":["-0.46042","49.12023"]},"properties":{"Date":"1944-07-18T00:00:00.000Z","Notes":"","UID":0,"SN":"43","MID":6,"UT":"Infantry","UC":"GB","US":"Division","LN":"43rd Infantry Division"}},{"type":"Feature","geometry":{"type":"Point","coordinates":["-0.73785","49.16816"]},"properties":{"Date":"1944-07-18T00:00:00.000Z","Notes":"","UID":0,"SN":"50","MID":6,"UT":"Infantry","UC":"GB","US":"Division","LN":"50th Infantry Division"}},{"type":"Feature","geometry":{"type":"Point","coordinates":["-1.00696","49.21391"]},"properties":{"Date":"1944-07-18T00:00:00.000Z","Notes":"","UID":0,"SN":"XIX","MID":26,"UT":"Infantry","UC":"USA","US":"Corp","LN":"Nineteenth Corps"}},{"type":"Feature","geometry":{"type":"Point","coordinates":["-0.92746","49.27338"]},"properties":{"Date":"1944-07-18T00:00:00.000Z","Notes":"","UID":0,"SN":"V","MID":26,"UT":"Infantry","UC":"USA","US":"Corp","LN":"Fifth Corps"}},{"type":"Feature","geometry":{"type":"Point","coordinates":["-1.16748","49.24788"]},"properties":{"Date":"1944-07-18T00:00:00.000Z","Notes":"","UID":0,"SN":"VII","MID":26,"UT":"Infantry","UC":"USA","US":"Corp","LN":"Seventh Corps"}},{"type":"Feature","geometry":{"type":"Point","coordinates":["-1.04861","49.29788"]},"properties":{"Date":"1944-07-18T00:00:00.000Z","Notes":"","UID":0,"SN":"First","MID":28,"UT":"Infantry","UC":"USA","US":"Army","LN":"First Army"}},{"type":"Feature","geometry":{"type":"Point","coordinates":["-0.48422","49.28161"]},"properties":{"Date":"1944-07-18T00:00:00.000Z","Notes":"","UID":0,"SN":"First","MID":34,"UT":"Infantry","UC":"CAN","US":"Army","LN":"First Army"}},{"type":"Feature","geometry":{"type":"Point","coordinates":["-1.19829","49.19188"]},"properties":{"Date":"1944-07-18T00:00:00.000Z","Notes":"","UID":0,"SN":"9","MID":25,"UT":"Infantry","UC":"USA","US":"Division","LN":"9th Infantry Division"}},{"type":"Feature","geometry":{"type":"Point","coordinates":["-1.19860","49.24926"]},"properties":{"Date":"1944-07-18T00:00:00.000Z","Notes":"","UID":0,"SN":"3","MID":30,"UT":"Armoured","UC":"USA","US":"Division","LN":"3rd Armoured Division"}},{"type":"Feature","geometry":{"type":"Point","coordinates":["-0.17104","49.23438"]},"properties":{"Date":"1944-07-18T00:00:00.000Z","Notes":"","UID":0,"SN":"711","MID":14,"UT":"Infantry","UC":"GMN","US":"Division","LN":"711th Infantry Division"}},{"type":"Feature","geometry":{"type":"Point","coordinates":["-0.52756","49.09405"]},"properties":{"Date":"1944-07-18T00:00:00.000Z","Notes":"","UID":0,"SN":"272","MID":14,"UT":"Infantry","UC":"GMN","US":"Division","LN":"272nd Infantry Division"}},{"type":"Feature","geometry":{"type":"Point","coordinates":["-0.16760","49.17766"]},"properties":{"Date":"1944-07-18T00:00:00.000Z","Notes":"","UID":0,"SN":"346","MID":14,"UT":"Infantry","UC":"GMN","US":"Division","LN":"346th Infantry Division"}},{"type":"Feature","geometry":{"type":"Point","coordinates":["-0.34253","49.08882"]},"properties":{"Date":"1944-07-18T00:00:00.000Z","Notes":"SS","UID":0,"SN":"12 SS","MID":19,"UT":"Armoured","UC":"GMN","US":"Division","LN":"12th SS Panzer Division"}},{"type":"Feature","geometry":{"type":"Point","coordinates":["-0.48985","49.07032"]},"properties":{"Date":"1944-07-18T00:00:00.000Z","Notes":"SS","UID":0,"SN":"9 SS","MID":19,"UT":"Armoured","UC":"GMN","US":"Division","LN":"9th SS Panzer Division"}},{"type":"Feature","geometry":{"type":"Point","coordinates":["-0.31195","49.12937"]},"properties":{"Date":"1944-07-18T00:00:00.000Z","Notes":"","UID":0,"SN":"21","MID":21,"UT":"Armoured","UC":"GMN","US":"Division","LN":"21st Panzer Division"}},{"type":"Feature","geometry":{"type":"Point","coordinates":["-0.81849","49.15319"]},"properties":{"Date":"1944-07-18T00:00:00.000Z","Notes":"","UID":0,"SN":"2","MID":30,"UT":"Armoured","UC":"USA","US":"Division","LN":"2nd Armoured Division"}},{"type":"Feature","geometry":{"type":"Point","coordinates":["-0.28291","49.15788"]},"properties":{"Date":"1944-07-18T00:00:00.000Z","Notes":"","UID":0,"SN":"11","MID":2,"UT":"Armoured","UC":"GB","US":"Division","LN":"11th Armoured Division"}},{"type":"Feature","geometry":{"type":"Point","coordinates":["-1.21495","49.14612"]},"properties":{"Date":"1944-07-18T00:00:00.000Z","Notes":"LEHR","UID":0,"SN":"Lehr","MID":21,"UT":"Armoured","UC":"GMN","US":"Division","LN":"Panzer Lehr Division"}},{"type":"Feature","geometry":{"type":"Point","coordinates":["-0.58808","49.08768"]},"properties":{"Date":"1944-07-18T00:00:00.000Z","Notes":"","UID":0,"SN":"271","MID":14,"UT":"Infantry","UC":"GMN","US":"Division","LN":"271st Infantry Division"}},{"type":"Feature","geometry":{"type":"Point","coordinates":["-0.65975","49.13787"]},"properties":{"Date":"1944-07-18T00:00:00.000Z","Notes":"","UID":0,"SN":"276","MID":14,"UT":"Infantry","UC":"GMN","US":"Division","LN":"276th Infantry Division"}},{"type":"Feature","geometry":{"type":"Point","coordinates":["-0.59561","49.11573"]},"properties":{"Date":"1944-07-18T00:00:00.000Z","Notes":"","UID":0,"SN":"277","MID":14,"UT":"Infantry","UC":"GMN","US":"Division","LN":"277th Infantry Division"}},{"type":"Feature","geometry":{"type":"Point","coordinates":["-1.31057","49.20558"]},"properties":{"Date":"1944-07-18T00:00:00.000Z","Notes":"","UID":0,"SN":"266","MID":14,"UT":"Infantry","UC":"GMN","US":"Division","LN":"266th Infantry Division"}},{"type":"Feature","geometry":{"type":"Point","coordinates":["-0.91257","49.06143"]},"properties":{"Date":"1944-07-18T00:00:00.000Z","Notes":"","UID":0,"SN":"3","MID":9,"UT":"Airborne","UC":"GMN","US":"Division","LN":"3rd Fallschirmjäger Division"}},{"type":"Feature","geometry":{"type":"Point","coordinates":["-0.32255","48.99993"]},"properties":{"Date":"1944-07-18T00:00:00.000Z","Notes":"SS","UID":0,"SN":"10 SS","MID":19,"UT":"Armoured","UC":"GMN","US":"Division","LN":"10th SS Panzer Division"}},{"type":"Feature","geometry":{"type":"Point","coordinates":["-0.58352","49.15870"]},"properties":{"Date":"1944-07-18T00:00:00.000Z","Notes":"","UID":0,"SN":"59","MID":6,"UT":"Infantry","UC":"GB","US":"Division","LN":"59th Infantry Division"}},{"type":"Feature","geometry":{"type":"Point","coordinates":["-1.06686","49.17777"]},"properties":{"Date":"1944-07-18T00:00:00.000Z","Notes":"","UID":0,"SN":"35","MID":25,"UT":"Infantry","UC":"USA","US":"Division","LN":"35th Infantry Division"}},{"type":"Feature","geometry":{"type":"Point","coordinates":["-0.50700","49.13380"]},"properties":{"Date":"1944-07-18T00:00:00.000Z","Notes":"","UID":0,"SN":"15","MID":6,"UT":"Infantry","UC":"GB","US":"Division","LN":"15th Infantry Division"}},{"type":"Feature","geometry":{"type":"Point","coordinates":["-1.03382","49.14975"]},"properties":{"Date":"1944-07-18T00:00:00.000Z","Notes":"","UID":0,"SN":"29","MID":25,"UT":"Infantry","UC":"USA","US":"Division","LN":"29th Infantry Division"}},{"type":"Feature","geometry":{"type":"Point","coordinates":["-0.93158","49.15256"]},"properties":{"Date":"1944-07-18T00:00:00.000Z","Notes":"","UID":0,"SN":"2","MID":25,"UT":"Infantry","UC":"USA","US":"Division","LN":"2nd Infantry Division"}},{"type":"Feature","geometry":{"type":"Point","coordinates":["-0.53800","49.22105"]},"properties":{"Date":"1944-07-18T00:00:00.000Z","Notes":"","UID":0,"SN":"XII","MID":5,"UT":"Infantry","UC":"GB","US":"Corp","LN":"Twelfth Corps"}},{"type":"Feature","geometry":{"type":"Point","coordinates":["-0.28472","48.94479"]},"properties":{"Date":"1944-07-18T00:00:00.000Z","Notes":"SS","UID":0,"SN":"I SS","MID":18,"UT":"Armoured","UC":"GMN","US":"Corp","LN":"First SS Panzer Corps"}},{"type":"Feature","geometry":{"type":"Point","coordinates":["-0.40076","48.93336"]},"properties":{"Date":"1944-07-18T00:00:00.000Z","Notes":"SS","UID":0,"SN":"II SS","MID":18,"UT":"Armoured","UC":"GMN","US":"Corp","LN":"Second SS Panzer Corps"}},{"type":"Feature","geometry":{"type":"Point","coordinates":["-1.51268","49.27019"]},"properties":{"Date":"1944-07-18T00:00:00.000Z","Notes":"","UID":0,"SN":"8","MID":25,"UT":"Infantry","UC":"USA","US":"Division","LN":"8th Infantry Division"}},{"type":"Feature","geometry":{"type":"Point","coordinates":["-1.28065","49.24397"]},"properties":{"Date":"1944-07-18T00:00:00.000Z","Notes":"","UID":0,"SN":"83","MID":25,"UT":"Infantry","UC":"USA","US":"Division","LN":"83rd Infantry Division"}},{"type":"Feature","geometry":{"type":"Point","coordinates":["-1.38063","49.39378"]},"properties":{"Date":"1944-07-18T00:00:00.000Z","Notes":"","UID":0,"SN":"VIII","MID":26,"UT":"Infantry","UC":"USA","US":"Corp","LN":"Eighth Corps"}},{"type":"Feature","geometry":{"type":"Point","coordinates":["-1.34180","49.12884"]},"properties":{"Date":"1944-07-18T00:00:00.000Z","Notes":"","UID":0,"SN":"LXXXIV","MID":13,"UT":"Infantry","UC":"GMN","US":"Corp","LN":"Eighty-fourth Corps"}},{"type":"Feature","geometry":{"type":"Point","coordinates":["-0.84728","49.11181"]},"properties":{"Date":"1944-07-18T00:00:00.000Z","Notes":"","UID":0,"SN":"1","MID":25,"UT":"Infantry","UC":"USA","US":"Division","LN":"1st Infantry Division"}},{"type":"Feature","geometry":{"type":"Point","coordinates":["-1.40844","49.28955"]},"properties":{"Date":"1944-07-18T00:00:00.000Z","Notes":"","UID":0,"SN":"90","MID":25,"UT":"Infantry","UC":"USA","US":"Division","LN":"90th Infantry Division"}},{"type":"Feature","geometry":{"type":"Point","coordinates":["-1.05459","49.09458"]},"properties":{"Date":"1944-07-18T00:00:00.000Z","Notes":"","UID":0,"SN":"352","MID":14,"UT":"Infantry","UC":"GMN","US":"Division","LN":"352nd Infantry Division"}},{"type":"Feature","geometry":{"type":"Point","coordinates":["-1.62129","49.29723"]},"properties":{"Date":"1944-07-18T00:00:00.000Z","Notes":"","UID":0,"SN":"79","MID":25,"UT":"Infantry","UC":"USA","US":"Division","LN":"79th Infantry Division"}},{"type":"Feature","geometry":{"type":"Point","coordinates":["-0.40480","49.10264"]},"properties":{"Date":"1944-07-18T00:00:00.000Z","Notes":"SS","UID":0,"SN":"1 SS","MID":19,"UT":"Armoured","UC":"GMN","US":"Division","LN":"1st SS Panzer Division"}},{"type":"Feature","geometry":{"type":"Point","coordinates":["-1.60488","49.21180"]},"properties":{"Date":"1944-07-18T00:00:00.000Z","Notes":"","UID":0,"SN":"353","MID":14,"UT":"Infantry","UC":"GMN","US":"Division","LN":"353rd Infantry Division"}},{"type":"Feature","geometry":{"type":"Point","coordinates":["-1.44164","49.17220"]},"properties":{"Date":"1944-07-18T00:00:00.000Z","Notes":"SS","UID":0,"SN":"2 SS","MID":19,"UT":"Armoured","UC":"GMN","US":"Division","LN":"2nd SS Panzer Division"}},{"type":"Feature","geometry":{"type":"Point","coordinates":["-0.53765","49.29520"]},"properties":{"Date":"1944-07-18T00:00:00.000Z","Notes":"","UID":0,"SN":"Second","MID":3,"UT":"Infantry","UC":"GB","US":"Army","LN":"Second Army"}},{"type":"Feature","geometry":{"type":"Point","coordinates":["-1.13828","49.17275"]},"properties":{"Date":"1944-07-18T00:00:00.000Z","Notes":"","UID":0,"SN":"30","MID":25,"UT":"Infantry","UC":"USA","US":"Division","LN":"30th Infantry Division"}},{"type":"Feature","geometry":{"type":"Point","coordinates":["-1.11392","48.98205"]},"properties":{"Date":"1944-07-18T00:00:00.000Z","Notes":"","UID":0,"SN":"II","MID":8,"UT":"Airborne","UC":"GMN","US":"Corp","LN":"Second Fallschirmjäger Corps"}},{"type":"Feature","geometry":{"type":"Point","coordinates":["-0.99643","49.29319"]},"properties":{"Date":"1944-07-18T00:00:00.000Z","Notes":"","UID":0,"SN":"1","MID":25,"UT":"Infantry","UC":"USA","US":"Division","LN":"1st Infantry Division"}},{"type":"Feature","geometry":{"type":"Point","coordinates":["-0.76580","49.06658"]},"properties":{"Date":"1944-07-18T00:00:00.000Z","Notes":"","UID":0,"SN":"2","MID":21,"UT":"Armoured","UC":"GMN","US":"Division","LN":"2nd Panzer Division"}},{"type":"Feature","geometry":{"type":"Point","coordinates":["-1.32312","49.18516"]},"properties":{"Date":"1944-07-18T00:00:00.000Z","Notes":"","UID":0,"SN":"17","MID":17,"UT":"Mechanized","UC":"GMN","US":"Division","LN":"17th Panzer Grenadier Division"}},{"type":"Feature","geometry":{"type":"Point","coordinates":["-0.23585","49.19109"]},"properties":{"Date":"1944-07-18T00:00:00.000Z","Notes":"","UID":0,"SN":"3","MID":6,"UT":"Infantry","UC":"GB","US":"Division","LN":"3rd Infantry Division"}},{"type":"Feature","geometry":{"type":"Point","coordinates":["-1.63388","49.25029"]},"properties":{"Date":"1944-07-18T00:00:00.000Z","Notes":"","UID":0,"SN":"243","MID":14,"UT":"Infantry","UC":"GMN","US":"Division","LN":"243rd Infantry Division"}},{"type":"Feature","geometry":{"type":"Point","coordinates":["-1.56305","49.22957"]},"properties":{"Date":"1944-07-18T00:00:00.000Z","Notes":"","UID":0,"SN":"91","MID":14,"UT":"Infantry","UC":"GMN","US":"Division","LN":"91st Infantry Division"}},{"type":"Feature","geometry":{"type":"Point","coordinates":["-1.47475","49.21669"]},"properties":{"Date":"1944-07-18T00:00:00.000Z","Notes":"","UID":0,"SN":"77","MID":14,"UT":"Infantry","UC":"GMN","US":"Division","LN":"77th Infantry Division"}},{"type":"Feature","geometry":{"type":"Point","coordinates":["-1.41878","49.22453"]},"properties":{"Date":"1944-07-18T00:00:00.000Z","Notes":"","UID":0,"SN":"265","MID":14,"UT":"Infantry","UC":"GMN","US":"Division","LN":"265th Infantry Division"}},{"type":"Feature","geometry":{"type":"Point","coordinates":["-1.30779","49.28250"]},"properties":{"Date":"1944-07-18T00:00:00.000Z","Notes":"","UID":0,"SN":"4","MID":25,"UT":"Infantry","UC":"USA","US":"Division","LN":"4th Infantry Division"}},{"type":"Feature","geometry":{"type":"Point","coordinates":["-0.63117","49.25488"]},"properties":{"Date":"1944-07-18T00:00:00.000Z","Notes":"","UID":0,"SN":"XXX","MID":5,"UT":"Infantry","UC":"GB","US":"Corp","LN":"Thirty Corps"}},{"type":"Feature","geometry":{"type":"Point","coordinates":["-0.42891","49.28791"]},"properties":{"Date":"1944-07-18T00:00:00.000Z","Notes":"","UID":0,"SN":"VIII","MID":5,"UT":"Infantry","UC":"GB","US":"Corp","LN":"Eigth Corps"}},{"type":"Feature","geometry":{"type":"Point","coordinates":["-1.34943","49.26234"]},"properties":{"Date":"1944-07-18T00:00:00.000Z","Notes":"","UID":0,"SN":"4","MID":30,"UT":"Armoured","UC":"USA","US":"Division","LN":"4th Armoured Division"}},{"type":"Feature","geometry":{"type":"Point","coordinates":["-0.35086","49.29117"]},"properties":{"Date":"1944-07-18T00:00:00.000Z","Notes":"","UID":0,"SN":"I","MID":5,"UT":"Infantry","UC":"GB","US":"Corp","LN":"First Corps"}},{"type":"Feature","geometry":{"type":"Point","coordinates":["-0.63111","49.33391"]},"properties":{"Date":"1944-07-18T00:00:00.000Z","Notes":"Guards","UID":0,"SN":"Guards","MID":2,"UT":"Armoured","UC":"GB","US":"Division","LN":"Guards Division"}},{"type":"Feature","geometry":{"type":"Point","coordinates":["-1.46398","49.10315"]},"properties":{"Date":"1944-07-18T00:00:00.000Z","Notes":"","UID":0,"SN":"343","MID":14,"UT":"Infantry","UC":"GMN","US":"Division","LN":"343rd Infantry Division"}},{"type":"Feature","geometry":{"type":"Point","coordinates":["-0.61892","48.84977"]},"properties":{"Date":"1944-07-18T00:00:00.000Z","Notes":"","UID":0,"SN":"XLVII","MID":20,"UT":"Armoured","UC":"GMN","US":"Corp","LN":"Fourty-seventh Panzer Corps"}},{"type":"Feature","geometry":{"type":"Point","coordinates":["-1.34962","49.21606"]},"properties":{"Date":"1944-07-18T00:00:00.000Z","Notes":"","UID":0,"SN":"6","MID":10,"UT":"Airborne","UC":"GMN","US":"Regiment","LN":"6 Regiment"}},{"type":"Feature","geometry":{"type":"Point","coordinates":["-0.25597","49.23082"]},"properties":{"Date":"1944-07-18T00:00:00.000Z","Notes":"","UID":320,"SN":"8th CIB","MID":35,"UT":"Infantry","UC":"CAN","US":"Brigade","LN":"8th Canadian Infantry Brigade"}},{"type":"Feature","geometry":{"type":"Point","coordinates":["-0.39146","49.25351"]},"properties":{"Date":"1944-07-18T00:00:00.000Z","Notes":"","UID":330,"SN":"9th CIB","MID":35,"UT":"Infantry","UC":"CAN","US":"Brigade","LN":"9th Canadian Infantry Brigade"}},{"type":"Feature","geometry":{"type":"Point","coordinates":["-0.38462","49.20915"]},"properties":{"Date":"1944-07-18T00:00:00.000Z","Notes":"","UID":310,"SN":"7th CIB","MID":35,"UT":"Infantry","UC":"CAN","US":"Brigade","LN":"7th Canadian Infantry Brigade"}},{"type":"Feature","geometry":{"type":"Point","coordinates":["-0.44669","49.15659"]},"properties":{"Date":"1944-07-18T00:00:00.000Z","Notes":"","UID":210,"SN":"4th CIB","MID":40,"UT":"Infantry","UC":"CAN","US":"Brigade","LN":"4th Canadian Infantry Brigade"}},{"type":"Feature","geometry":{"type":"Point","coordinates":["-0.45036","49.17487"]},"properties":{"Date":"1944-07-18T00:00:00.000Z","Notes":"","UID":230,"SN":"6th CIB","MID":40,"UT":"Infantry","UC":"CAN","US":"Brigade","LN":"6th Canadian Infantry Brigade"}},{"type":"Feature","geometry":{"type":"Point","coordinates":["-0.47116","49.21696"]},"properties":{"Date":"1944-07-18T00:00:00.000Z","Notes":"","UID":200,"SN":"2nd CID","MID":37,"UT":"Infantry","UC":"CAN","US":"Division","LN":"2nd Canadian Infantry Division"}},{"type":"Feature","geometry":{"type":"Point","coordinates":["-0.28779","49.21676"]},"properties":{"Date":"1944-07-18T00:00:00.000Z","Notes":"QOR Bn HQ","UID":321,"SN":"QOR","MID":45,"UT":"Infantry","UC":"CAN","US":"Battalion","LN":"The Queen?s Own Rifles of Canadaÿ"}},{"type":"Feature","geometry":{"type":"Point","coordinates":["-0.31688","49.18178"]},"properties":{"Date":"1944-07-18T00:00:00.000Z","Notes":"North Nova","UID":333,"SN":"NNSH","MID":45,"UT":"Infantry","UC":"CAN","US":"Battalion","LN":"The North Nova Scotia Highlanders"}},{"type":"Feature","geometry":{"type":"Point","coordinates":["-0.30649","49.19464"]},"properties":{"Date":"1944-07-18T00:00:00.000Z","Notes":"North Shore","UID":322,"SN":"NS Regt","MID":45,"UT":"Infantry","UC":"CAN","US":"Battalion","LN":"North Shore (New Brunswick) Regiment"}},{"type":"Feature","geometry":{"type":"Point","coordinates":["-0.38422","49.20889"]},"properties":{"Date":"1944-07-18T00:00:00.000Z","Notes":"CSCOTR","UID":311,"SN":"CScotR","MID":45,"UT":"Infantry","UC":"CAN","US":"Battalion","LN":"The Canadian Scottish Regiment"}},{"type":"Feature","geometry":{"type":"Point","coordinates":["-0.37557","49.19451"]},"properties":{"Date":"1944-07-18T00:00:00.000Z","Notes":"RRR","UID":312,"SN":"Regina","MID":45,"UT":"Infantry","UC":"CAN","US":"Battalion","LN":"The Regina Rifles"}},{"type":"Feature","geometry":{"type":"Point","coordinates":["-0.37603","49.19385"]},"properties":{"Date":"1944-07-18T00:00:00.000Z","Notes":"RWR","UID":313,"SN":"RWR","MID":45,"UT":"Infantry","UC":"CAN","US":"Battalion","LN":"The Royal Winnipeg Rifles"}},{"type":"Feature","geometry":{"type":"Point","coordinates":["-0.31688","49.18178"]},"properties":{"Date":"1944-07-18T00:00:00.000Z","Notes":"","UID":331,"SN":"HLI of C","MID":45,"UT":"Infantry","UC":"CAN","US":"Battalion","LN":"Highland Light Infantry of Canada"}},{"type":"Feature","geometry":{"type":"Point","coordinates":["-0.30194","49.19706"]},"properties":{"Date":"1944-07-18T00:00:00.000Z","Notes":"","UID":332,"SN":"SD&G","MID":45,"UT":"Infantry","UC":"CAN","US":"Battalion","LN":"Stormont, Dundas & Glengarry Highlanders"}},{"type":"Feature","geometry":{"type":"Point","coordinates":["-0.30186","49.19672"]},"properties":{"Date":"1944-07-18T00:00:00.000Z","Notes":"<Null>","UID":21,"SN":"6th CAR","MID":48,"UT":"Armoured","UC":"CAN","US":"Battalion","LN":"6th Canadian Armoured Regiment (1st Hussars)ÿ"}},{"type":"Feature","geometry":{"type":"Point","coordinates":["-0.37346","49.19321"]},"properties":{"Date":"1944-07-18T00:00:00.000Z","Notes":"<Null>","UID":363,"SN":"7th Recce","MID":56,"UT":"Reconnaissance","UC":"CAN","US":"Battalion","LN":"7th Reconnaissance Regiment (17th Duke of York's Royal Canadian Hussars)"}},{"type":"Feature","geometry":{"type":"Point","coordinates":["-0.34784","49.21799"]},"properties":{"Date":"1944-07-18T00:00:00.000Z","Notes":"<Null>","UID":351,"SN":"12th RCA","MID":52,"UT":"Artillery","UC":"CAN","US":"Battalion","LN":"12th Field Regiment Royal Canadian Artillery"}},{"type":"Feature","geometry":{"type":"Point","coordinates":["-0.34815","49.22845"]},"properties":{"Date":"1944-07-18T00:00:00.000Z","Notes":"<Null>","UID":352,"SN":"13th RCA","MID":52,"UT":"Artillery","UC":"CAN","US":"Battalion","LN":"13th Field Regiment Royal Canadian Artillery"}},{"type":"Feature","geometry":{"type":"Point","coordinates":["-0.34284","49.22234"]},"properties":{"Date":"1944-07-18T00:00:00.000Z","Notes":"<Null>","UID":353,"SN":"14th RCA","MID":52,"UT":"Artillery","UC":"CAN","US":"Battalion","LN":"14th Field Regiment Royal Canadian Artillery"}},{"type":"Feature","geometry":{"type":"Point","coordinates":["-0.34813","49.26793"]},"properties":{"Date":"1944-07-18T00:00:00.000Z","Notes":"<Null>","UID":23,"SN":"27th CAR","MID":48,"UT":"Armoured","UC":"CAN","US":"Battalion","LN":"27th Canadian Armoured Regiment (The Sherbrooke Fusiliers)ÿ"}},{"type":"Feature","geometry":{"type":"Point","coordinates":["-0.43248","49.19054"]},"properties":{"Date":"1944-07-18T00:00:00.000Z","Notes":"<Null>","UID":220,"SN":"5th CIB","MID":40,"UT":"Infantry","UC":"CAN","US":"Brigade","LN":"5th Canadian Infantry Brigade"}},{"type":"Feature","geometry":{"type":"Point","coordinates":["-0.37691","49.23091"]},"properties":{"Date":"1944-07-18T00:00:00.000Z","Notes":"","UID":354,"SN":"19th RCA","MID":52,"UT":"Artillery","UC":"CAN","US":"Battalion","LN":"19th Field Regiment Royal Canadian Artillery"}},{"type":"Feature","geometry":{"type":"Point","coordinates":["-0.43495","49.15733"]},"properties":{"Date":"1944-07-18T00:00:00.000Z","Notes":"","UID":211,"SN":"RRegtC","MID":44,"UT":"Infantry","UC":"CAN","US":"Battalion","LN":"The Royal Regiment of Canada"}},{"type":"Feature","geometry":{"type":"Point","coordinates":["-0.38223","49.20786"]},"properties":{"Date":"1944-07-18T00:00:00.000Z","Notes":"","UID":20,"SN":"2nd CAB","MID":43,"UT":"Armoured","UC":"CAN","US":"Brigade","LN":"2nd Canadian Armoured Brigade"}},{"type":"Feature","geometry":{"type":"Point","coordinates":["-0.43239","49.14380"]},"properties":{"Date":"1944-07-18T00:00:00.000Z","Notes":"","UID":212,"SN":"ESR","MID":44,"UT":"Infantry","UC":"CAN","US":"Battalion","LN":"Essex Scottish Regiment"}},{"type":"Feature","geometry":{"type":"Point","coordinates":["-0.39667","49.17661"]},"properties":{"Date":"1944-07-18T00:00:00.000Z","Notes":"","UID":221,"SN":"Calgary","MID":44,"UT":"Infantry","UC":"CAN","US":"Battalion","LN":"The Calgary Highlanders"}},{"type":"Feature","geometry":{"type":"Point","coordinates":["-0.42618","49.15599"]},"properties":{"Date":"1944-07-18T00:00:00.000Z","Notes":"","UID":213,"SN":"RHLI","MID":44,"UT":"Infantry","UC":"CAN","US":"Battalion","LN":"Royal Hamilton Light Infantry"}},{"type":"Feature","geometry":{"type":"Point","coordinates":["-0.44521","49.18919"]},"properties":{"Date":"1944-07-18T00:00:00.000Z","Notes":"","UID":232,"SN":"QOC","MID":44,"UT":"Infantry","UC":"CAN","US":"Battalion","LN":"Queen's Own Cameron Highlanders of Canada"}},{"type":"Feature","geometry":{"type":"Point","coordinates":["-0.40080","49.18626"]},"properties":{"Date":"1944-07-18T00:00:00.000Z","Notes":"Posn Unknown","UID":222,"SN":"Maison","MID":44,"UT":"Infantry","UC":"CAN","US":"Battalion","LN":"Le Regiment de Maisonneuve"}},{"type":"Feature","geometry":{"type":"Point","coordinates":["-0.44766","49.16873"]},"properties":{"Date":"1944-07-18T00:00:00.000Z","Notes":"Exact Posn Unknown","UID":231,"SN":"Mont-Royal","MID":44,"UT":"Infantry","UC":"CAN","US":"Battalion","LN":"Les Fusiliers Mont-Royal"}},{"type":"Feature","geometry":{"type":"Point","coordinates":["-0.35936","49.16664"]},"properties":{"Date":"1944-07-18T00:00:00.000Z","Notes":"Exact Posn Unknown","UID":223,"SN":"Black Watch","MID":44,"UT":"Infantry","UC":"CAN","US":"Battalion","LN":"The Black Watch (Royal Highalnders) of Canada"}},{"type":"Feature","geometry":{"type":"Point","coordinates":["-0.47927","49.18066"]},"properties":{"Date":"1944-07-18T00:00:00.000Z","Notes":"","UID":233,"SN":"SSR","MID":44,"UT":"Infantry","UC":"CAN","US":"Battalion","LN":"The South Sasketchewan Regiment"}},{"type":"Feature","geometry":{"type":"Point","coordinates":["-0.25260","49.25684"]},"properties":{"Date":"1944-07-18T00:00:00.000Z","Notes":"","UID":1,"SN":"1 Can Para","MID":50,"UT":"Airborne","UC":"CAN","US":"Battalion","LN":"1st Canadian Parachute Battalion"}},{"type":"Feature","geometry":{"type":"Point","coordinates":["-0.38831","49.23642"]},"properties":{"Date":"1944-07-18T00:00:00.000Z","Notes":"","UID":365,"SN":"6th RCE","MID":58,"UT":"Engineer","UC":"CAN","US":"Company","LN":"6th Field Company, Royal Canadian Engineers"}},{"type":"Feature","geometry":{"type":"Point","coordinates":["-0.48146","49.20547"]},"properties":{"Date":"1944-07-18T00:00:00.000Z","Notes":"","UID":300,"SN":"3rd CID","MID":39,"UT":"Infantry","UC":"CAN","US":"Division","LN":"3rd Canadian Infantry Division"}},{"type":"Feature","geometry":{"type":"Point","coordinates":["-0.43773","49.15198"]},"properties":{"Date":"1944-07-18T00:00:00.000Z","Notes":"","UID":22,"SN":"10th CAR","MID":48,"UT":"Armoured","UC":"CAN","US":"Battalion","LN":"10th Canadian Armoured Regiment (The Fort Garry Horse)"}},{"type":"Feature","geometry":{"type":"Point","coordinates":["-0.47988","49.17386"]},"properties":{"Date":"1944-07-18T00:00:00.000Z","Notes":"","UID":252,"SN":"5th RCA","MID":51,"UT":"Artillery","UC":"CAN","US":"Battalion","LN":"5th Field Regiment, Royal Canadian Artillery"}},{"type":"Feature","geometry":{"type":"Point","coordinates":["-0.47026","49.17292"]},"properties":{"Date":"1944-07-18T00:00:00.000Z","Notes":"","UID":253,"SN":"6th RCA","MID":51,"UT":"Artillery","UC":"CAN","US":"Battalion","LN":"6th Field Regiment, Royal Canadian Artillery"}},{"type":"Feature","geometry":{"type":"Point","coordinates":["-0.47808","49.16227"]},"properties":{"Date":"1944-07-18T00:00:00.000Z","Notes":"","UID":251,"SN":"4th RCA","MID":51,"UT":"Artillery","UC":"CAN","US":"Battalion","LN":"4th Field Regiment, Royal Canadian Artillery"}},{"type":"Feature","geometry":{"type":"Point","coordinates":["-0.40689","49.16222"]},"properties":{"Date":"1944-07-18T00:00:00.000Z","Notes":"<Null>","UID":261,"SN":"8th Recce","MID":55,"UT":"Reconnaissance","UC":"CAN","US":"Battalion","LN":"8th Reconnaissance Regiment (14th Canadian Hussars)"}},{"type":"Feature","geometry":{"type":"Point","coordinates":["-0.32254","49.17721"]},"properties":{"Date":"1944-07-18T00:00:00.000Z","Notes":"","UID":323,"SN":"Chaud","MID":44,"UT":"Infantry","UC":"Can","US":"Battalion","LN":"Regiment de la Chaudiere"}},{"type":"Feature","geometry":{"type":"Point","coordinates":["-0.39155","49.22805"]},"properties":{"Date":"1944-07-18T00:00:00.000Z","Notes":"","UID":368,"SN":"18th RCE","MID":65,"UT":"Engineer","UC":"CAN","US":"Company","LN":"18th Field Company Royal Canadian Engineers"}},{"type":"Feature","geometry":{"type":"Point","coordinates":["-0.34703","49.21392"]},"properties":{"Date":"1944-07-18T00:00:00.000Z","Notes":"<Null>","UID":370,"SN":"5th RCE","MID":65,"UT":"Engineer","UC":"CAN","US":"Company","LN":"5th Field Company Royal Canadian Engineers"}},{"type":"Feature","geometry":{"type":"Point","coordinates":["-0.39140","49.22829"]},"properties":{"Date":"1944-07-18T00:00:00.000Z","Notes":"<Null>","UID":367,"SN":"16th RCE","MID":58,"UT":"Engineer","UC":"CAN","US":"Company","LN":"16th Field Company Royal Canadian Engineers"}},{"type":"Feature","geometry":{"type":"Point","coordinates":["-0.38361","49.23139"]},"properties":{"Date":"1944-07-18T00:00:00.000Z","Notes":"","UID":364,"SN":"Camerons","MID":62,"UT":"Infantry","UC":"CAN","US":"Battalion","LN":"The Cameron Highlanders of Ottawa (Duke of Edinburgh's Own)"}},{"type":"Feature","geometry":{"type":"Point","coordinates":["-0.38778","49.20972"]},"properties":{"Date":"1944-07-18T00:00:00.000Z","Notes":"","UID":364,"SN":"Camerons","MID":63,"UT":"Infantry","UC":"CAN","US":"Company","LN":"The Cameron Highlanders of Ottawa (Duke of Edinburgh's Own)"}},{"type":"Feature","geometry":{"type":"Point","coordinates":["-0.38917","49.20861"]},"properties":{"Date":"1944-07-18T00:00:00.000Z","Notes":"","UID":364,"SN":"Camerons","MID":63,"UT":"Infantry","UC":"CAN","US":"Company","LN":"The Cameron Highlanders of Ottawa (Duke of Edinburgh's Own)"}},{"type":"Feature","geometry":{"type":"Point","coordinates":["-0.34897","49.21581"]},"properties":{"Date":"1944-07-18T00:00:00.000Z","Notes":"","UID":364,"SN":"Camerons","MID":64,"UT":"Infantry","UC":"CAN","US":"Platoon","LN":"The Cameron Highlanders of Ottawa (Duke of Edinburgh's Own)"}},{"type":"Feature","geometry":{"type":"Point","coordinates":["-0.38917","49.20861"]},"properties":{"Date":"1944-07-18T00:00:00.000Z","Notes":"","UID":364,"SN":"Camerons","MID":63,"UT":"Infantry","UC":"CAN","US":"Company","LN":"The Cameron Highlanders of Ottawa (Duke of Edinburgh's Own)"}},{"type":"Feature","geometry":{"type":"Point","coordinates":["-0.38592","49.23225"]},"properties":{"Date":"1944-07-18T00:00:00.000Z","Notes":"","UID":364,"SN":"Camerons","MID":63,"UT":"Infantry","UC":"CAN","US":"Company","LN":"The Cameron Highlanders of Ottawa (Duke of Edinburgh's Own)"}}]}